paperazzi/__about__.py
paperazzi/__init__.py
paperazzi/compute_cost.py
paperazzi/config.py
paperazzi/log.py
paperazzi/utils.py
paperazzi/platforms/__init__.py
paperazzi/platforms/utils.py
paperazzi/platforms/instructor/__init__.py
paperazzi/platforms/instructor/utils.py
paperazzi/platforms/mistralai/__init__.py
paperazzi/platforms/mistralai/utils.py
paperazzi/platforms/openai/__init__.py
paperazzi/platforms/openai/utils.py
paperazzi/platforms/vertexai/__init__.py
paperazzi/platforms/vertexai/utils.py
paperazzi/structured_output/__init__.py
paperazzi/structured_output/utils.py
paperazzi/structured_output/autaff/__init__.py
paperazzi/structured_output/autaff/analysis.py
paperazzi/structured_output/autaff/evaluate.py
paperazzi/structured_output/autaff/model.py
paperazzi/structured_output/autaff/model_v1.py
paperazzi/structured_output/autaff/model_v2.py
paperazzi/structured_output/autaff/model_v3.py
paperazzi/structured_output/autaffhtml/__init__.py
paperazzi/structured_output/autaffhtml/analysis.py
paperazzi/structured_output/autaffhtml/evaluate.py
paperazzi/structured_output/autaffhtml/model.py
paperazzi/structured_output/autaffhtml/model_v1.py
paperazzi/structured_output/autaffpdf/__init__.py
paperazzi/structured_output/autaffpdf/analysis.py
paperazzi/structured_output/autaffpdf/evaluate.py
paperazzi/structured_output/autaffpdf/model.py
paperazzi/structured_output/autaffpdf/model_v1.py
paperazzi/structured_output/autaffpdf/model_v2.py
paperazzi/structured_output/autaffpdf/model_v3.py
paperazzi/structured_output/parsepdf/__init__.py
paperazzi/structured_output/parsepdf/model.py
paperazzi/structured_output/parsepdf/model_v0.py
paperazzi/structured_output/parsepdf/ocr.py
paperazzi/config.ini
paperazzi-0.0.7.dist-info/METADATA
paperazzi-0.0.7.dist-info/WHEEL
paperazzi-0.0.7.dist-info/licenses/LICENSE.txt
paperazzi-0.0.7.dist-info/RECORD
